{
  "meta": {
    "title": "UANE - Experiencia que transforma, Inscríbete",
    "description": "Conoce todos los programas académicos de UANE: Bachillerato, Licenciaturas, Ingenierías, Maestrídas, Especialidades, Doctorados y Programas Internacionales",
    "keywords": ""
  },
  "sections": {
    "head": {
      "banner": 
        {
          "width": "100%",
          "height": "600px",
          "iconleft": "arrow_back_ios",
          "iconright": "arrow_forward_ios",
          "slides": [
            {
              "title": "Estudia una carrera a tu ritmo ¡y aprovecha tu fin de semana!", 
              "text": "Carreras sabatinas con sesiones de 4 horas.",
              "urlImage": {
                "mobile": "https://www.uane.edu.mx/multi/images/programas/becas.jpg",
                "desktop": "https://www.uane.edu.mx/multi/images/programas/becas.jpg"
              },
              "center": true,
              "left": false,
              "middle": true,
              "bottom": false
            },
            {
              "title": "Conecta con el mundo", 
              "text": "UANE te da acceso a diferentes programas internacionales con movilidad al extranjero y en línea.",
              "urlImage": {
                "mobile": "https://www.uane.edu.mx/multi/images/programas/becas.jpg",
                "desktop": "https://www.uane.edu.mx/multi/images/programas/becas.jpg"
              },
              "center": true,
              "left": false,
              "middle": true,
              "bottom": false
            },
            {
              "title": "¡Tenemos vacantes nuevas!", 
              "text": "Accede y descubre las oportunidades que tenemos para ti.",
              "urlImage": {
                "mobile": "https://www.uane.edu.mx/multi/images/programas/becas.jpg",
                "desktop": "https://www.uane.edu.mx/multi/images/programas/becas.jpg"
              },
              "center": true,
              "left": false,
              "middle": true,
              "bottom": false
            }
          ]
        }
    },
    "oferta": {
      "title": "¿Qué me ofrece UANE para estudiar?",
      "levels": [
        {
          "level": "bachillerato",
          "title": "Bachillerato",
          "promo": {
            "urlImage": {
              "mobile": "https://image.shutterstock.com/image-photo/young-student-woman-isolated-on-260nw-1932261476.jpg",
              "desktop": "https://image.shutterstock.com/image-photo/young-student-woman-isolated-on-260nw-1932261476.jpg"
            },
            "text": "Bachillerato",
            "icon": "arrow_forward",
            "color": "#D5583E",
            "opacity": "multiply",
            "height": "282px",
            "enable": true,
            "nobackground": false
          }
        },
        {
          "level": "licenciatura",
          "title": "Licenciaturas",
          "promo": {
            "urlImage": {
              "mobile": "https://image.shutterstock.com/image-photo/young-student-woman-isolated-on-260nw-1932261476.jpg",
              "desktop": "https://image.shutterstock.com/image-photo/young-student-woman-isolated-on-260nw-1932261476.jpg"
            },
            "text": "Licenciaturas",
            "icon": "arrow_forward",
            "color": "#42C1A6",
            "opacity": "multiply",
            "height": "282px",
            "enable": true,
            "nobackground": false
          }
        },
        {
          "level": "especialidad",
          "title": "Especialidades",
          "promo": {
            "urlImage": {
              "mobile": "https://image.shutterstock.com/image-photo/young-student-woman-isolated-on-260nw-1932261476.jpg",
              "desktop": "https://image.shutterstock.com/image-photo/young-student-woman-isolated-on-260nw-1932261476.jpg"
            },
            "text": "Especialidades",
            "icon": "arrow_forward",
            "color": "#9E5ED3",
            "opacity": "multiply",
            "height": "282px",
            "enable": true,
            "nobackground": false
          }
        },
        {
          "level": "maestria",
          "title": "Maestrias",
          "promo": {
            "urlImage": {
              "mobile": "https://image.shutterstock.com/image-photo/young-student-woman-isolated-on-260nw-1932261476.jpg",
              "desktop": "https://image.shutterstock.com/image-photo/young-student-woman-isolated-on-260nw-1932261476.jpg"
            },
            "text": "Maestrias",
            "icon": "arrow_forward",
            "color": "#5ED365",
            "opacity": "multiply",
            "height": "282px",
            "enable": true,
            "nobackground": false
          }
        },
        {
          "level": "doctorado",
          "title": "Doctorado",
          "promo": {
            "urlImage": {
              "mobile": "https://image.shutterstock.com/image-photo/young-student-woman-isolated-on-260nw-1932261476.jpg",
              "desktop": "https://image.shutterstock.com/image-photo/young-student-woman-isolated-on-260nw-1932261476.jpg"
            },
            "text": "Doctorado",
            "icon": "arrow_forward",
            "color": "#D35EA3",
            "opacity": "multiply",
            "height": "282px",
            "enable": true,
            "nobackground": false
          }
        }
      ]
    },
    "banner-internacional": {
      "title": "UANE Internacional",
      "subtitle": "internacionalízate agrega experiencias internacionales a tu educación",
      "state": "black",
      "size": "medium",
      "middle": false,
      "center": false,
      "bottom": false,
      "left": false,
      "urlImage": {
        "mobile": "https://cdn.milenio.com/uploads/media/2020/01/31/reconocio-alumnos-obtuvieron-promedios-mayores.jpg",
        "desktop": "https://cdn.milenio.com/uploads/media/2020/01/31/reconocio-alumnos-obtuvieron-promedios-mayores.jpg"
      },
      "overlay": "black",
      "height": "",
      "action": {
        "id": "",
        "type": "outlined",
        "title": "Conocer más",
        "size": "small",
        "icon": "",
        "lyIcon": false,
        "disabled": false,
        "isExpand": false,
        "tagOnClick": "",
        "test": ""
      },
      "wrapper": true
    },
    "numbers":[
      { "icon": "apartment", "prefix": "", "number": "8", "suffix": "", "title": "Campus en el país", "body": "", "container": true },
      { "icon": "manage_history", "prefix": "+", "number": "48", "suffix": "+", "title": "Años de experiencia", "body": "", "container": true },
      { "icon": "group", "prefix": "+", "number": "12500", "suffix": "+", "title": "Alumnos Inscritos", "body": "", "container": true },
      { "icon": "history_edu", "prefix": "+", "number": "48000", "suffix": "+", "title": "Egresados", "body": "", "container": true }
    ],
    "vozUane": {
      "title": "Voz UANE blog",
      "notas": [
        { 
          "urlImage": "https://image.shutterstock.com/image-photo/graduates-student-graduation-caps-thrown-260nw-1937758900.jpg",
          "subtitle": "SUBTITULO",
          "title": "Coursera y UANE se unen para ti",
          "text": "Se firma una alianza con Coursera para acceder a contenidos que complementen la formación profesional de su comunidad educativa",
          "border": true,
          "allContent": true,
          "height": "",
          "isShowCardWebsiteContent": true,
          "id": "",
          "type": "vertical",
          "link": true,
          "background": false,
          "linkText": {
            "text": "Conocer más",
            "isBold": true,
            "size": "large",
            "isUnderline": false,
            "disabled": false,
            "icon": "star"
          },
          "linkIcon": {
            "text": "Ver más",
            "iconSecond": "person",
            "isBold": true,
            "size": "large",
            "isUnderline": false,
            "disabled": false,
            "icon": "person"
          },
          "wrapper": true
        },
        { 
          "urlImage": "https://image.shutterstock.com/image-photo/graduates-student-graduation-caps-thrown-260nw-1937758900.jpg",
          "subtitle": "SUBTITULO",
          "title": "Coursera y UANE se unen para ti",
          "text": "Se firma una alianza con Coursera para acceder a contenidos que complementen la formación profesional de su comunidad educativa",
          "border": true,
          "allContent": true,
          "height": "",
          "isShowCardWebsiteContent": true,
          "id": "",
          "type": "vertical",
          "link": true,
          "background": false,
          "linkText": {
            "text": "Conocer más",
            "isBold": true,
            "size": "large",
            "isUnderline": false,
            "disabled": false,
            "icon": "star"
          },
          "linkIcon": {
            "text": "Ver más",
            "iconSecond": "person",
            "isBold": true,
            "size": "large",
            "isUnderline": false,
            "disabled": false,
            "icon": "person"
          },
          "wrapper": true
        },
        { 
          "urlImage": "https://image.shutterstock.com/image-photo/graduates-student-graduation-caps-thrown-260nw-1937758900.jpg",
          "subtitle": "SUBTITULO",
          "title": "Coursera y UANE se unen para ti",
          "text": "Se firma una alianza con Coursera para acceder a contenidos que complementen la formación profesional de su comunidad educativa",
          "border": true,
          "allContent": true,
          "height": "",
          "isShowCardWebsiteContent": true,
          "id": "",
          "type": "vertical",
          "link": true,
          "background": false,
          "linkText": {
            "text": "Conocer más",
            "isBold": true,
            "size": "large",
            "isUnderline": false,
            "disabled": false,
            "icon": "star"
          },
          "linkIcon": {
            "text": "Ver más",
            "iconSecond": "person",
            "isBold": true,
            "size": "large",
            "isUnderline": false,
            "disabled": false,
            "icon": "person"
          },
          "wrapper": true
        }
      ]
    },
    "banner-podcast":{
      "title": "Podcast Voz UANE",
      "subtitle": "Un espisodio nuevo cada 2 semanas en Spotify y Youtube",
      "state": "black",
      "size": "medium",
      "middle": false,
      "center": false,
      "bottom": false,
      "left": false,
      "urlImage": {
        "mobile": "https://home.kpmg/content/dam/kpmg/es/images/2021/01/podcast-1500x857.jpg",
        "desktop": "https://home.kpmg/content/dam/kpmg/es/images/2021/01/podcast-1500x857.jpg"
      },
      "overlay": "black",
      "height": "",
      "action": {
        "id": "",
        "type": "outlined",
        "title": "Conocer más",
        "size": "small",
        "icon": "",
        "lyIcon": false,
        "disabled": false,
        "isExpand": false,
        "tagOnClick": "testClick",
        "test": ""
      },
      "wrapper": true
    },
    "descubre": {
      "title": "Descubre más de la vida UANE",
      "options": {
        "id": "Ae84Xfec1HM",
        "type": "single",
        "controls": true
      },
      "dimensions": {
        "height": "500px"
      }
    }
  }
}